__init__.py
dropgrad/__init__.py
dropgrad/dropgrad_opt.py
test/__init__.py
test/test.py
dropgrad_dingo_actual-0.1.0.dist-info/LICENSE
dropgrad_dingo_actual-0.1.0.dist-info/METADATA
dropgrad_dingo_actual-0.1.0.dist-info/WHEEL
dropgrad_dingo_actual-0.1.0.dist-info/top_level.txt
dropgrad_dingo_actual-0.1.0.dist-info/RECORD
