Metadata-Version: 2.1
Name: dropgrad_dingo-actual
Version: 0.1.0
Summary: A PyTorch implementation of DropGrad regularization.
Author-email: Ryan Taylor <ryan@beta-reduce.net>
Maintainer-email: Ryan Taylor <ryan@beta-reduce.net>
License: MIT License
Project-URL: Repository, https://github.com/dingo-actual/dropgrad
Project-URL: Homepage, https://github.com/dingo-actual/dropgrad
Project-URL: Issues, https://github.com/dingo-actual/dropgrad/issues
Keywords: neural networks,machine learning,pytorch
Classifier: Programming Language :: Python :: 3
Classifier: Development Status :: 4 - Beta
Classifier: Intended Audience :: Science/Research
Classifier: License :: OSI Approved :: MIT License
Classifier: Natural Language :: English
Classifier: Topic :: Scientific/Engineering :: Artificial Intelligence
Classifier: Operating System :: OS Independent
Requires-Python: >=3.7
License-File: LICENSE
Requires-Dist: pytorch
